LICENCE.txt
README.md
setup.cfg
setup.py
pybulldozer/__init__.py
pybulldozer/__main__.py
pybulldozer/fileparser.py
pybulldozer/helpers.py
pybulldozer/loddict.py
pybulldozer/parsing_strats.py
pybulldozer.egg-info/PKG-INFO
pybulldozer.egg-info/SOURCES.txt
pybulldozer.egg-info/dependency_links.txt
pybulldozer.egg-info/requires.txt
pybulldozer.egg-info/top_level.txt
pybulldozer/__pycache__/__init__.cpython-39.pyc
pybulldozer/__pycache__/fileparser.cpython-39.pyc
pybulldozer/__pycache__/helpers.cpython-39.pyc
pybulldozer/__pycache__/loddict.cpython-39.pyc
pybulldozer/__pycache__/parsing_strats.cpython-39.pyc
pybulldozer/general/node.py
pybulldozer/general/structure.py
pybulldozer/general/__pycache__/node.cpython-39.pyc
pybulldozer/general/__pycache__/structure.cpython-39.pyc
pybulldozer/general_cy/node.cp39-win_amd64.pyd
pybulldozer/general_cy/node.pyi
pybulldozer/general_cy/node.pyx
pybulldozer/general_cy/structure.cp39-win_amd64.pyd
pybulldozer/general_cy/structure.pyi
pybulldozer/general_cy/structure.pyx
test/test_example.py
test/test_functions.py