Metadata-Version: 2.1
Name: pybulldozer
Version: 0.0.4
Summary: pybulldozer aims to make working with non-relation data files as easy as possible
Home-page: https://github.com/mike-huls/pybulldozer
Author: Mike Huls
Author-email: mikehuls42@gmail.com
License: MIT
Platform: UNKNOWN
Classifier: Development Status :: 3 - Alpha
Classifier: Intended Audience :: Developers
Classifier: License :: OSI Approved :: MIT License
Classifier: Programming Language :: Python :: 3
License-File: LICENCE.txt
